README.md
setup.py
no_cap/__init__.py
no_cap.egg-info/PKG-INFO
no_cap.egg-info/SOURCES.txt
no_cap.egg-info/dependency_links.txt
no_cap.egg-info/requires.txt
no_cap.egg-info/top_level.txt